easyzip/__init__.py
easyzip/easyzip.py
easyzip-1.0.2.dist-info/LICENSE
easyzip-1.0.2.dist-info/METADATA
easyzip-1.0.2.dist-info/WHEEL
easyzip-1.0.2.dist-info/top_level.txt
easyzip-1.0.2.dist-info/RECORD
