Metadata-Version: 2.1
Name: easyzip
Version: 1.0.2
Summary: Easy zip file or directory with password
Home-page: https://github.com/hewenhan/easyzip
Author: Blind Holmes
Author-email: hewenhan@gmail.com
License: UNKNOWN
Platform: UNKNOWN
Classifier: Programming Language :: Python :: 3
Classifier: License :: OSI Approved :: MIT License
Classifier: Operating System :: OS Independent
License-File: LICENSE
Requires-Dist: pyminizip
